[
  {
    "name": "Advanced Authentication",
    "description": "Lorem Lorem Lorem Lorem Lorem Lorem Lorem Lorem Lorem Lorem Lorem",
    "thumbNailUrl": "/projects/project1.png",
    "liveLink": "https://authorization-sharath.vercel.app",
    "isLive": true,
    "githubLink": "",
    "badges": [
      "NextJS",
      "Typescript",
      "bcryptjs",
      "bcryptjs",
      "bcryptjs",
      "bcryptjs"
    ]
  },
  {
    "name": "Advanced Authentication",
    "description": "Lorem Lorem Lorem Lorem Lorem Lorem Lorem Lorem Lorem Lorem Lorem",
    "thumbNailUrl": "/projects/project1.png",
    "liveLink": "https://authorization-sharath.vercel.app",
    "isLive": true,
    "githubLink": "",
    "badges": [
      "NextJS",
      "Typescript",
      "bcryptjs",
      "bcryptjs",
      "bcryptjs",
      "bcryptjs"
    ]
  },
  {
    "name": "Advanced Authentication",
    "description": "Lorem Lorem Lorem Lorem Lorem Lorem Lorem Lorem Lorem Lorem Lorem",
    "thumbNailUrl": "/projects/project1.png",
    "liveLink": "https://authorization-sharath.vercel.app",
    "isLive": true,
    "githubLink": "",
    "badges": [
      "NextJS",
      "Typescript",
      "bcryptjs",
      "bcryptjs",
      "bcryptjs",
      "bcryptjs"
    ]
  },
  {
    "name": "Advanced Authentication",
    "description": "Lorem Lorem Lorem Lorem Lorem Lorem Lorem Lorem Lorem Lorem Lorem",
    "thumbNailUrl": "/projects/project1.png",
    "liveLink": "https://authorization-sharath.vercel.app",
    "isLive": true,
    "githubLink": "",
    "badges": [
      "NextJS",
      "Typescript",
      "bcryptjs",
      "bcryptjs",
      "bcryptjs",
      "bcryptjs"
    ]
  },
  {
    "name": "Advanced Authentication",
    "description": "Lorem Lorem Lorem Lorem Lorem Lorem Lorem Lorem Lorem Lorem Lorem",
    "thumbNailUrl": "/projects/project1.png",
    "liveLink": "https://authorization-sharath.vercel.app",
    "isLive": true,
    "githubLink": "",
    "badges": [
      "NextJS",
      "Typescript",
      "bcryptjs",
      "bcryptjs",
      "bcryptjs",
      "bcryptjs"
    ]
  },
  {
    "name": "Advanced Authentication",
    "description": "Lorem Lorem Lorem Lorem Lorem Lorem Lorem Lorem Lorem Lorem Lorem",
    "thumbNailUrl": "/projects/project1.png",
    "liveLink": "https://authorization-sharath.vercel.app",
    "isLive": true,
    "githubLink": "",
    "badges": [
      "NextJS",
      "Typescript",
      "bcryptjs",
      "bcryptjs",
      "bcryptjs",
      "bcryptjs"
    ]
  },
  {
    "name": "Advanced Authentication",
    "description": "Lorem Lorem Lorem Lorem Lorem Lorem Lorem Lorem Lorem Lorem Lorem",
    "thumbNailUrl": "/projects/project1.png",
    "liveLink": "https://authorization-sharath.vercel.app",
    "isLive": true,
    "githubLink": "",
    "badges": [
      "NextJS",
      "Typescript",
      "bcryptjs",
      "bcryptjs",
      "bcryptjs",
      "bcryptjs"
    ]
  }
]
